raspi_version.py
setup.py
raspi_version.egg-info/PKG-INFO
raspi_version.egg-info/SOURCES.txt
raspi_version.egg-info/dependency_links.txt
raspi_version.egg-info/top_level.txt