Metadata-Version: 1.1
Name: raspi-version
Version: 0.1.0
Summary: Python 2 and 3 compatibility utilities
Home-page: https://github.com/tompreston/raspi-version
Author: Thomas Preston
Author-email: thomasmarkpreston+raspiversion@gmail.com
License: MIT
Platform: UNKNOWN
Classifier: Programming Language :: Python :: 2
Classifier: Programming Language :: Python :: 3
Classifier: Intended Audience :: Developers
Classifier: License :: OSI Approved :: MIT License
Classifier: Topic :: Software Development :: Libraries
Classifier: Topic :: Utilities
